xomics/__init__.py
xomics/_data/__init__.py
xomics/_utils/__init__.py
xomics/_utils/check_data.py
xomics/_utils/check_models.py
xomics/_utils/check_type.py
xomics/_utils/decorators.py
xomics/_utils/new_types.py
xomics/_utils/utils_output.py
xomics/config.py
xomics/data_handling/__init__.py
xomics/data_handling/_data_process.py
xomics/imputation/__init__.py
xomics/imputation/_backend/__init__.py
xomics/imputation/_c_impute.py
xomics/integration/__init__.py
xomics/integration/_integrate.py
xomics/plotting/__init__.py
xomics/plotting/_plot_get_clist.py
xomics/plotting/_plot_settings.py
xomics/plotting/_plotting.py
xomics/plotting/utils_plotting.py
xomics/ranking/__init__.py
xomics/ranking/_enrichment_hits.py
xomics/ranking/_scoring.py
xomics/template_classes.py
xomics/utils.py
xomics-0.2.0.dist-info/LICENSE
xomics-0.2.0.dist-info/METADATA
xomics-0.2.0.dist-info/WHEEL
xomics-0.2.0.dist-info/RECORD
