Metadata-Version: 2.1
Name: xomics
Version: 0.2.0
Summary: Python framework for eXplainable Omics analysis
License: MIT
Author: Stephan Breimann
Author-email: stephanbreimann@gmail.de
Requires-Python: >=3.9,<=3.11
Classifier: Development Status :: 3 - Alpha
Classifier: Intended Audience :: Developers
Classifier: Intended Audience :: Science/Research
Classifier: License :: OSI Approved :: MIT License
Classifier: Natural Language :: English
Classifier: Operating System :: OS Independent
Classifier: Programming Language :: Python :: 3
Classifier: Programming Language :: Python :: 3.9
Classifier: Programming Language :: Python :: 3.10
Classifier: Programming Language :: Python :: 3.11
Classifier: Topic :: Scientific/Engineering
Classifier: Topic :: Scientific/Engineering :: Artificial Intelligence
Classifier: Topic :: Scientific/Engineering :: Bio-Informatics
Requires-Dist: Pillow (>=9.2.0,<10.0.0)
Requires-Dist: cycler (>=0.11.0,<0.12.0)
Requires-Dist: et-xmlfile (>=1.1.0,<2.0.0)
Requires-Dist: fonttools (>=4.37.1,<5.0.0)
Requires-Dist: joblib (>=1.1.0,<2.0.0)
Requires-Dist: kiwisolver (>=1.4.4,<2.0.0)
Requires-Dist: matplotlib (>=3.5.3,<4.0.0)
Requires-Dist: numpy (>=1.24.4,<2.0.0)
Requires-Dist: openpyxl (>=3.0.10,<4.0.0)
Requires-Dist: packaging (>=21.3,<22.0)
Requires-Dist: pandas (>=2.0.0,<=2.1)
Requires-Dist: patsy (>=0.5.2,<0.6.0)
Requires-Dist: pip (>=23.2.01,<24.0.0)
Requires-Dist: pyparsing (>=3.0.9,<4.0.0)
Requires-Dist: python-dateutil (>=2.8.2,<3.0.0)
Requires-Dist: pytz (>=2022.2.1,<2023.0.0)
Requires-Dist: scikit-learn (>=1.1.2,<2.0.0)
Requires-Dist: scipy (>=1.9.0,<2.0.0)
Requires-Dist: seaborn (>=0.11.2,<0.12.0)
Requires-Dist: six (>=1.16.0,<2.0.0)
Requires-Dist: statsmodels (>=0.13.2,<0.14.0)
Requires-Dist: threadpoolctl (>=3.1.0,<4.0.0)
Project-URL: Documentation, https://xomics.readthedocs.io
Project-URL: Repository, https://github.com/breimanntools/xomics
